Workbook

Sheet Dashboard
A1: OCTDEC | EXECUTIVE DASHBOARD
A2: K-Beauty for Every Budget — 3-Year Financial Model Summary | Business Plan, July 2026
B4: TOTAL STARTUP COST | D4: YEAR 3 REVENUE | F4: YEAR 3 NET PROFIT | H4: GROSS MARGIN
B5: ='Startup Cost'!D15 -> 920000 | D5: ='Revenue Projection'!E7 -> 450 | F5: ='P&L Statement'!E19 -> 40.5 | H5: =Assumptions!C11 -> 0.53846154
B6: ₹ | D6: ₹ Lakh | F6: ₹ Lakh
B8: BREAK-EVEN UNITS | D8: YEAR 3 UNITS SOLD | F8: REVENUE CAGR (Y1-Y3) | H8: YEAR 3 NET MARGIN
B9: ='Break-even Analysis'!C14 -> 10414.286 | D9: ='Revenue Projection'!C7 -> 346153.85 | F9: ='Revenue Projection'!E8 -> 2.1622777 | H9: ='P&L Statement'!E20 -> 0.09
B10: units | D10: units
B31: Cost Category | C31: Year 3 (₹ Lakh)
B32: COGS | C32: ='P&L Statement'!E7 -> 166.32
B33: Marketing | C33: ='P&L Statement'!E12 -> 110.88
B34: Logistics | C34: ='P&L Statement'!E13 -> 59.4
B35: Overhead | C35: ='P&L Statement'!E14 -> 59.4

Sheet Assumptions
A1: OCTDEC | FINANCIAL MODEL
A2: Assumptions Sheet — All inputs driving the 3-Year Financial Model | Figures in ₹ unless stated
B4: 1. UNIT ECONOMICS (Per Kit)
B5: Assumption | C5: Value | D5: Notes / Source
B6: Selling Price per Kit (MRP) | C6: 130 | E6: Business Plan §13.2 / §25.1 — anchor retail price
B7: Cost of Goods Sold (COGS) per Kit | C7: 45 | E7: Business Plan §25.1 — serum, capsules, pouch
B8: Packaging, Logistics & Handling per Kit | C8: 15 | E8: Business Plan §25.1
B9: Total Variable Cost per Kit | C9: =C7+C8 -> 60 | E9: Sum of COGS + Packaging/Logistics
B10: Contribution Margin per Kit | C10: =C6-C9 -> 70 | E10: Business Plan §25.1 — ≈ ₹70 (54%)
B11: Gross Margin % of Selling Price | C11: =C10/C6 -> 0.53846154 | E11: Business Plan §25.1 — ≈54%
B13: 2. REVENUE & VOLUME ASSUMPTIONS (3-Year Plan)
B14: Assumption | C14: Value | D14: Notes / Source
B15: Year 1 Revenue (₹ Lakh) | C15: 45 | E15: Business Plan §30.1
B16: Year 2 Revenue (₹ Lakh) | C16: 180 | E16: Business Plan §30.1
B17: Year 3 Revenue (₹ Lakh) | C17: 450 | E17: Business Plan §30.1
B18: Year 1→2 Growth Multiple | C18: 4 | E18: Business Plan §30.1
B19: Year 2→3 Growth Multiple | C19: 2.5 | E19: Business Plan §30.1
B21: 3. COST STRUCTURE ASSUMPTIONS (% of Total Operating Cost)
B22: Assumption | C22: Value | D22: Notes / Source
B23: Cost of Goods Sold — % of Total Cost | C23: 0.42 | E23: Business Plan §31.1
B24: Marketing — % of Total Cost | C24: 0.28 | E24: Business Plan §31.1
B25: Logistics — % of Total Cost | C25: 0.15 | E25: Business Plan §31.1
B26: Overhead / Admin — % of Total Cost | C26: 0.15 | E26: Business Plan §31.1
B27: Check — Cost Structure Sums to 100% | C27: =SUM(C23:C26) -> 1
B28: Total Operating Cost ÷ Revenue — Year 1 | C28: 1.08 | E28: Derived from Business Plan §31.1 (₹48.60L / ₹45.00L)
B29: Total Operating Cost ÷ Revenue — Year 2 | C29: 0.96 | E29: Derived from Business Plan §31.1 (₹172.80L / ₹180.00L)
B30: Total Operating Cost ÷ Revenue — Year 3 | C30: 0.88 | E30: Derived from Business Plan §31.1 (₹396.00L / ₹450.00L)
B32: 4. STARTUP, TAX & WORKING CAPITAL ASSUMPTIONS (Illustrative where noted)
B33: Assumption | C33: Value | D33: Notes / Source
B34: Total Estimated Startup Cost (₹) | C34: 920000 | E34: Business Plan §29
B35: Corporate Tax Rate (illustrative) | C35: 0.25 | E35: ILLUSTRATIVE — approx. Indian domestic co. concessional rate; not stated in Business Plan
B36: Working Capital Buffer / Contingency (₹) | C36: 80000 | E36: Business Plan §29 (~10% of startup cost)
B37: Inflation / Cost Escalation p.a. (illustrative) | C37: 0 | E37: ILLUSTRATIVE — not modelled; Business Plan holds unit economics constant across 3 yrs (§28)
B38: Opening Cash Injection (Founder Capital) (₹) | C38: 920000 | E38: ILLUSTRATIVE — assumed equal to startup cost, Business Plan §28.1 (no debt financing)
B40: 5. BREAK-EVEN INPUTS (carried from Business Plan §32)
B41: Assumption | C41: Value | D41: Notes / Source
B42: Year 1 Fixed Overhead (₹) | C42: 729000 | E42: Business Plan §31.1 / §32.1
B45: Colour key: Blue = hardcoded input | Black = formula | Green = link from another sheet
B46: All figures are drawn directly from the OCTDEC Business Plan (July 2026) unless flagged ILLUSTRATIVE.

Sheet Startup Cost
A1: OCTDEC | STARTUP COST
A2: One-time and initial working-capital costs to bring the business from concept to first commercial sale (Business Plan §29)
B4: Category | C4: Description | D4: Estimated Cost (₹) | E4: % of Total
B5: Company Registration & Legal | C5: Pvt. Ltd. formation, trademark filing | D5: 60000 | E5: =D5/$D$15 -> 0.065217391
B6: Product R&D & Formulation | C6: Contract lab work, 4-variant development | D6: 150000 | E6: =D6/$D$15 -> 0.16304348
B7: Initial Inventory Production | C7: Batch 1, ~6,000 units at ₹45 COGS | D7: 270000 | E7: =D7/$D$15 -> 0.29347826
B8: Packaging & Brand Identity Design | C8: Pouch, capsule packaging, logo system | D8: 80000 | E8: =D8/$D$15 -> 0.086956522
B9: Website & D2C Storefront Setup | C9: E-commerce platform, WhatsApp Business API | D9: 50000 | E9: =D9/$D$15 -> 0.054347826
B10: Initial Marketing & Launch Campaign | C10: Influencer seeding, campus activation, content | D10: 120000 | E10: =D10/$D$15 -> 0.13043478
B11: Quick-Commerce Onboarding & Listing Fees | C11: Blinkit / Zepto / Instamart | D11: 40000 | E11: =D11/$D$15 -> 0.043478261
B12: Photography, Content & Product Sampling | C12: Photography, content production & sampling | D12: 30000 | E12: =D12/$D$15 -> 0.032608696
B13: Basic Operations Setup | C13: Equipment, minimal workspace | D13: 40000 | E13: =D13/$D$15 -> 0.043478261
B14: Working Capital Buffer & Contingency | C14: ~10% contingency reserve | D14: 80000 | E14: =D14/$D$15 -> 0.086956522
B15: GRAND TOTAL | D15: =SUM(D5:D14) -> 920000 | E15: =SUM(E5:E14) -> 1
B17: Note: At approximately ₹9.2 lakh, total startup cost reflects an asset-light, contract-manufactured launch (Business Plan §29).
B19: Cross-check vs. Assumptions sheet (Total Startup Cost) | D19: =Assumptions!C34-D15 -> 0

Sheet Revenue Projection
A1: OCTDEC | REVENUE PROJECTION
A2: 3-Year Revenue Plan — driven by phased go-to-market strategy (Business Plan §22, §30)
B4: Year | C4: Units Sold | D4: Selling Price (₹) | E4: Revenue (₹ Lakh) | F4: Growth (x Prior Yr)
B5: Year 1 | C5: =Assumptions!C15*100000/Assumptions!$C$6 -> 34615.385 | D5: =Assumptions!$C$6 -> 130 | E5: =Assumptions!C15 -> 45 | F5: —
B6: Year 2 | C6: =Assumptions!C16*100000/Assumptions!$C$6 -> 138461.54 | D6: =Assumptions!$C$6 -> 130 | E6: =Assumptions!C16 -> 180 | F6: =E6/E5 -> 4
B7: Year 3 | C7: =Assumptions!C17*100000/Assumptions!$C$6 -> 346153.85 | D7: =Assumptions!$C$6 -> 130 | E7: =Assumptions!C17 -> 450 | F7: =E7/E6 -> 2.5
B8: CAGR (Year 1 → Year 3) | E8: =(E7/E5)^(1/2)-1 -> 2.1622777
B10: Units Sold = Revenue ÷ Selling Price per Kit (Business Plan §30.1). Revenue grows ~10x from Year 1 to Year 3, ahead of category CAGR (~9.4%) due to India's D2C beauty segment CAGR of ~36.4% (Business Plan §9).

Sheet P&L Statement
A1: OCTDEC | PROFIT & LOSS STATEMENT
A2: 3-Year P&L — ₹ Lakh | Cost structure applied per Business Plan §31.1
B4: Line Item | C4: Year 1 | D4: Year 2 | E4: Year 3
B5: Revenue | C5: ='Revenue Projection'!E5 -> 45 | D5: ='Revenue Projection'!E6 -> 180 | E5: ='Revenue Projection'!E7 -> 450
B6: Total Operating Cost | C6: =C5*Assumptions!$C$28 -> 48.6 | D6: =D5*Assumptions!$C$29 -> 172.8 | E6: =E5*Assumptions!$C$30 -> 396
B7: Cost of Goods Sold (COGS) | C7: =C6*Assumptions!$C$23 -> 20.412 | D7: =D6*Assumptions!$C$23 -> 72.576 | E7: =E6*Assumptions!$C$23 -> 166.32
B8: Gross Profit | C8: =C5-C7 -> 24.588 | D8: =D5-D7 -> 107.424 | E8: =E5-E7 -> 283.68
B9: Gross Margin % | C9: =C8/C5 -> 0.5464 | D9: =D8/D5 -> 0.5968 | E9: =E8/E5 -> 0.6304
B11: Operating Expenses:
B12: Marketing | C12: =C6*Assumptions!$C$24 -> 13.608 | D12: =D6*Assumptions!$C$24 -> 48.384 | E12: =E6*Assumptions!$C$24 -> 110.88
B13: Logistics | C13: =C6*Assumptions!$C$25 -> 7.29 | D13: =D6*Assumptions!$C$25 -> 25.92 | E13: =E6*Assumptions!$C$25 -> 59.4
B14: Administrative Expenses (Overhead) | C14: =C6*Assumptions!$C$26 -> 7.29 | D14: =D6*Assumptions!$C$26 -> 25.92 | E14: =E6*Assumptions!$C$26 -> 59.4
B15: Total Operating Expenses | C15: =SUM(C12:C14) -> 28.188 | D15: =SUM(D12:D14) -> 100.224 | E15: =SUM(E12:E14) -> 229.68
B17: Net Profit / (Loss) — Pre-Tax | C17: =C8-C15 -> -3.6 | D17: =D8-D15 -> 7.2 | E17: =E8-E15 -> 54
B18: Income Tax (illustrative, only if profitable) | C18: =MAX(C17,0)*Assumptions!$C$35 -> 0 | D18: =MAX(D17,0)*Assumptions!$C$35 -> 1.8 | E18: =MAX(E17,0)*Assumptions!$C$35 -> 13.5
B19: Net Profit / (Loss) — After Tax | C19: =C17-C18 -> -3.6 | D19: =D17-D18 -> 5.4 | E19: =E17-E18 -> 40.5
B20: Net Margin % | C20: =C19/C5 -> -0.08 | D20: =D19/D5 -> 0.03 | E20: =E19/E5 -> 0.09
B22: Cost ratios (Total Cost ÷ Revenue) and cost-mix splits are taken directly from Business Plan §31.1 and remain fully formula-linked to the Assumptions sheet. Tax is illustrative and applied only in profitable years.

Sheet Break-even Analysis
A1: OCTDEC | BREAK-EVEN ANALYSIS
A2: Unit-level operating break-even and investment break-even (Business Plan §32)
B4: 1. CONTRIBUTION MARGIN
B5: Metric | C5: Value | D5: Notes
B6: Selling Price per Unit | C6: =Assumptions!C6 -> 130 | D6: Business Plan §32.1
B7: Variable Cost per Unit (COGS + Logistics) | C7: =Assumptions!C9 -> 60 | D7: Business Plan §32.1
B8: Contribution Margin per Unit | C8: =C6-C7 -> 70 | D8: ≈ ₹70 (54%) — Business Plan §32.1
B9: Contribution Margin % | C9: =C8/C6 -> 0.53846154
B11: 2. UNIT-LEVEL OPERATING BREAK-EVEN (Year 1 overhead only)
B12: Metric | C12: Value | D12: Notes
B13: Year 1 Fixed Overhead | C13: =Assumptions!C42 -> 729000 | D13: Business Plan §31.1 / §32.1
B14: Break-even Volume (Units) | C14: =C13/C8 -> 10414.286 | D14: ≈ 10,414 units — Business Plan §32.1
B15: Break-even Revenue (₹) | C15: =C14*C6 -> 1353857.1 | D15: ≈ ₹13.5 lakh — Business Plan §32.1
B17: 3. INVESTMENT BREAK-EVEN (Full Startup Cost Recovery)
B18: Metric | C18: Value | D18: Notes
B19: Total Estimated Startup Cost | C19: =Assumptions!C34 -> 920000 | D19: Business Plan §29
B20: Investment Break-even Volume (Units) | C20: =C19/C8 -> 13142.857 | D20: ≈ 13,140 units — Business Plan §32.2
B21: Investment Break-even Revenue (₹) | C21: =C20*C6 -> 1708571.4 | D21: ≈ ₹17.1 lakh — Business Plan §32.2
B22: Year 1 Projected Revenue (₹) | C22: =Assumptions!C15*100000 -> 4500000
B23: Illustrative Months to Investment Break-even | C23: =(C21/C22)*12 -> 4.5561905 | D23: Assumes even monthly sales distribution across Year 1 — Business Plan §32.2 notes actual ramp likely back-loaded
B25: 4. BREAK-EVEN SENSITIVITY — Revenue vs. Cost Line (Illustrative Volume Scenarios)
B26: Units Sold | C26: Total Revenue (₹) | D26: Total Cost (₹)
B27: 0 | C27: =B27*$C$6 -> 0 | D27: =B27*$C$7+$C$13 -> 729000
B28: 2000 | C28: =B28*$C$6 -> 260000 | D28: =B28*$C$7+$C$13 -> 849000
B29: 4000 | C29: =B29*$C$6 -> 520000 | D29: =B29*$C$7+$C$13 -> 969000
B30: 6000 | C30: =B30*$C$6 -> 780000 | D30: =B30*$C$7+$C$13 -> 1089000
B31: 8000 | C31: =B31*$C$6 -> 1040000 | D31: =B31*$C$7+$C$13 -> 1209000
B32: 10000 | C32: =B32*$C$6 -> 1300000 | D32: =B32*$C$7+$C$13 -> 1329000
B33: 12000 | C33: =B33*$C$6 -> 1560000 | D33: =B33*$C$7+$C$13 -> 1449000
B34: 14000 | C34: =B34*$C$6 -> 1820000 | D34: =B34*$C$7+$C$13 -> 1569000
B35: 16000 | C35: =B35*$C$6 -> 2080000 | D35: =B35*$C$7+$C$13 -> 1689000
B36: 18000 | C36: =B36*$C$6 -> 2340000 | D36: =B36*$C$7+$C$13 -> 1809000
B37: 20000 | C37: =B37*$C$6 -> 2600000 | D37: =B37*$C$7+$C$13 -> 1929000

Sheet Cash Flow
A1: OCTDEC | CASH FLOW STATEMENT
A2: Year 1 Monthly Cash Flow (illustrative ramp) + 3-Year Annual Summary | Figures in ₹ unless stated
B4: 1. YEAR 1 — MONTHLY CASH FLOW (ILLUSTRATIVE — monthly split not specified in Business Plan; weighted toward H2 per §32.2)
B5: Line Item | C5: Apr | D5: May | E5: Jun | F5: Jul | G5: Aug | H5: Sep | I5: Oct | J5: Nov | K5: Dec | L5: Jan | M5: Feb | N5: Mar
B6: Revenue Weighting % (illustrative) | C6: 0.03 | D6: 0.04 | E6: 0.05 | F6: 0.06 | G6: 0.07 | H6: 0.08 | I6: 0.09 | J6: 0.1 | K6: 0.1 | L6: 0.11 | M6: 0.12 | N6: 0.15
B7: Revenue | C7: =C6*Assumptions!$C$15*100000 -> 135000 | D7: =D6*Assumptions!$C$15*100000 -> 180000 | E7: =E6*Assumptions!$C$15*100000 -> 225000 | F7: =F6*Assumptions!$C$15*100000 -> 270000 | G7: =G6*Assumptions!$C$15*100000 -> 315000 | H7: =H6*Assumptions!$C$15*100000 -> 360000 | I7: =I6*Assumptions!$C$15*100000 -> 405000 | J7: =J6*Assumptions!$C$15*100000 -> 450000 | ... N7: =N6*Assumptions!$C$15*100000 -> 675000
B8: Variable Cost (COGS + Packaging) | C8: =C7/Assumptions!$C$6*Assumptions!$C$9 -> 62307.692 | D8: =D7/Assumptions!$C$6*Assumptions!$C$9 -> 83076.923 | E8: =E7/Assumptions!$C$6*Assumptions!$C$9 -> 103846.15 | F8: =F7/Assumptions!$C$6*Assumptions!$C$9 -> 124615.38 | G8: =G7/Assumptions!$C$6*Assumptions!$C$9 -> 145384.62 | H8: =H7/Assumptions!$C$6*Assumptions!$C$9 -> 166153.85 | I8: =I7/Assumptions!$C$6*Assumptions!$C$9 -> 186923.08 | J8: =J7/Assumptions!$C$6*Assumptions!$C$9 -> 207692.31 | ... N8: =N7/Assumptions!$C$6*Assumptions!$C$9 -> 311538.46
B9: Fixed Costs (Marketing + Logistics + Overhead, spread evenly) | C9: =('P&L Statement'!C12+'P&L Statement'!C13+'P&L Statement'!C14)*100000/12 -> 234900 | D9: =('P&L Statement'!C12+'P&L Statement'!C13+'P&L Statement'!C14)*100000/12 -> 234900 | E9: =('P&L Statement'!C12+'P&L Statement'!C13+'P&L Statement'!C14)*100000/12 -> 234900 | F9: =('P&L Statement'!C12+'P&L Statement'!C13+'P&L Statement'!C14)*100000/12 -> 234900 | G9: =('P&L Statement'!C12+'P&L Statement'!C13+'P&L Statement'!C14)*100000/12 -> 234900 | H9: =('P&L Statement'!C12+'P&L Statement'!C13+'P&L Statement'!C14)*100000/12 -> 234900 | I9: =('P&L Statement'!C12+'P&L Statement'!C13+'P&L Statement'!C14)*100000/12 -> 234900 | J9: =('P&L Statement'!C12+'P&L Statement'!C13+'P&L Statement'!C14)*100000/12 -> 234900 | K9: =('P&L Statement'!C12+'P&L Statement'!C13+'P&L Statement'!C14)*100000/12 -> 234900 | L9: =('P&L Statement'!C12+'P&L Statement'!C13+'P&L Statement'!C14)*100000/12 -> 234900 | M9: =('P&L Statement'!C12+'P&L Statement'!C13+'P&L Statement'!C14)*100000/12 -> 234900 | N9: =('P&L Statement'!C12+'P&L Statement'!C13+'P&L Statement'!C14)*100000/12 -> 234900
B10: Total Cash Outflow | C10: =C8+C9 -> 297207.69 | D10: =D8+D9 -> 317976.92 | E10: =E8+E9 -> 338746.15 | F10: =F8+F9 -> 359515.38 | G10: =G8+G9 -> 380284.62 | H10: =H8+H9 -> 401053.85 | I10: =I8+I9 -> 421823.08 | J10: =J8+J9 -> 442592.31 | ... N10: =N8+N9 -> 546438.46
B11: Net Cash Flow for the Month | C11: =C7-C10 -> -162207.69 | D11: =D7-D10 -> -137976.92 | E11: =E7-E10 -> -113746.15 | F11: =F7-F10 -> -89515.385 | G11: =G7-G10 -> -65284.615 | H11: =H7-H10 -> -41053.846 | I11: =I7-I10 -> -16823.077 | J11: =J7-J10 -> 7407.6923 | ... N11: =N7-N10 -> 128561.54
B12: Opening Cash Balance | C12: =Assumptions!$C$38 -> 920000 | D12: =C13 -> 757792.31 | E12: =D13 -> 619815.38 | F12: =E13 -> 506069.23 | G12: =F13 -> 416553.85 | H12: =G13 -> 351269.23 | I12: =H13 -> 310215.38 | J12: =I13 -> 293392.31 | K12: =J13 -> 300800 | ... N12: =M13 -> 395715.38
B13: Closing Cash Balance | C13: =C12+C11 -> 757792.31 | D13: =D12+D11 -> 619815.38 | E13: =E12+E11 -> 506069.23 | F13: =F12+F11 -> 416553.85 | G13: =G12+G11 -> 351269.23 | H13: =H12+H11 -> 310215.38 | I13: =I12+I11 -> 293392.31 | J13: =J12+J11 -> 300800 | ... N13: =N12+N11 -> 524276.92
B15: Monthly revenue split is an ILLUSTRATIVE planning assumption (weighted toward H2, consistent with Business Plan §32.2's note that early months likely see lower volumes as brand awareness builds). Fixed costs are spread evenly across the year.
B18: 2. 3-YEAR ANNUAL CASH FLOW SUMMARY (₹ Lakh)
B19: Line Item | C19: Year 1 | D19: Year 2 | E19: Year 3
B20: Opening Cash Balance | C20: =Assumptions!C38/100000 -> 9.2 | D20: =C24 -> 5.6 | E20: =D24 -> 12.8
B21: Cash Inflow (Revenue) | C21: ='P&L Statement'!C5 -> 45 | D21: ='P&L Statement'!D5 -> 180 | E21: ='P&L Statement'!E5 -> 450
B22: Cash Outflow (Total Operating Cost) | C22: ='P&L Statement'!C6 -> 48.6 | D22: ='P&L Statement'!D6 -> 172.8 | E22: ='P&L Statement'!E6 -> 396
B23: Net Cash Flow for the Year | C23: =C21-C22 -> -3.6 | D23: =D21-D22 -> 7.2 | E23: =E21-E22 -> 54
B24: Closing Cash Balance | C24: =C20+C23 -> 5.6 | D24: =D20+D23 -> 12.8 | E24: =E20+E23 -> 66.8
B26: Annual summary reconciles directly to the P&L Statement sheet (fully formula-linked). Opening cash for Year 1 equals the founder-capital injection assumed in the Assumptions sheet.
